rwmpf.py
RadiumWMPFInstaller-0.1.4.dist-info/METADATA
RadiumWMPFInstaller-0.1.4.dist-info/WHEEL
RadiumWMPFInstaller-0.1.4.dist-info/entry_points.txt
RadiumWMPFInstaller-0.1.4.dist-info/top_level.txt
RadiumWMPFInstaller-0.1.4.dist-info/RECORD
