Metadata-Version: 2.1
Name: RadiumWMPFInstaller
Version: 0.1.4
Summary: RadiumWMPF installer
Home-page: https://github.com/r3x5ur/RadiumWMPFInstaller
Author: r3x5ur
Author-email: me@example.com
License: MIT
Classifier: License :: OSI Approved :: MIT License
Classifier: Environment :: Win32 (MS Windows)
Classifier: Environment :: Console
Classifier: Operating System :: Microsoft :: Windows
Classifier: Programming Language :: Python
Classifier: Programming Language :: Python :: 3
Classifier: Programming Language :: Python :: 3.6
Classifier: Programming Language :: Python :: Implementation :: CPython
Classifier: Programming Language :: Python :: Implementation :: PyPy
Requires-Python: >=3.6.0
Requires-Dist: requests
Requires-Dist: lxml
Requires-Dist: questionary
